nativehello/__init__.py
nativehello/greetings.py
nativehello-0.1.0.dist-info/METADATA
nativehello-0.1.0.dist-info/WHEEL
nativehello-0.1.0.dist-info/top_level.txt
nativehello-0.1.0.dist-info/RECORD
