Metadata-Version: 2.4
Name: nativehello
Version: 0.1.0
Summary: A package that says Hello World in various native languages
Keywords: hello world greetings languages
Dynamic: keywords
Dynamic: summary
